.coveragerc
.editorconfig
.gitignore
.travis.yml
LICENSE
README.md
setup.cfg
setup.py
tox.ini
chilero/__init__.py
chilero/pg/__init__.py
chilero/pg/application.py
chilero/pg/connection.py
chilero/pg/resource.py
chilero/pg/test.py
chilero/pg/utils.py
chilero_pg.egg-info/PKG-INFO
chilero_pg.egg-info/SOURCES.txt
chilero_pg.egg-info/dependency_links.txt
chilero_pg.egg-info/namespace_packages.txt
chilero_pg.egg-info/requires.txt
chilero_pg.egg-info/top_level.txt
tests/conftest.py
tests/test_db.py
tests/test_sample_app.py
tests/test_utils.py
tests/data/db.sql