Metadata-Version: 1.0
Name: chilero-pg
Version: 0.4.0
Summary: PostgreSQL utilities for chilero
Home-page: https://github.com/dmonroy/chilero.pg
Author: Darwin Monroy
Author-email: contact@darwinmonroy.com
License: UNKNOWN
Platform: UNKNOWN
